CMakeLists.txt
LICENSE
MANIFEST.in
NOTICE
README.rst
pyproject.toml
setup.cfg
setup.py
include/ssapy.h
llnl_ssapy.egg-info/PKG-INFO
llnl_ssapy.egg-info/SOURCES.txt
llnl_ssapy.egg-info/dependency_links.txt
llnl_ssapy.egg-info/not-zip-safe
llnl_ssapy.egg-info/requires.txt
llnl_ssapy.egg-info/top_level.txt
pybind11/CMakeLists.txt
pybind11/LICENSE
pybind11/include/pybind11/attr.h
pybind11/include/pybind11/buffer_info.h
pybind11/include/pybind11/cast.h
pybind11/include/pybind11/chrono.h
pybind11/include/pybind11/common.h
pybind11/include/pybind11/complex.h
pybind11/include/pybind11/eigen.h
pybind11/include/pybind11/embed.h
pybind11/include/pybind11/eval.h
pybind11/include/pybind11/functional.h
pybind11/include/pybind11/gil.h
pybind11/include/pybind11/gil_safe_call_once.h
pybind11/include/pybind11/iostream.h
pybind11/include/pybind11/numpy.h
pybind11/include/pybind11/operators.h
pybind11/include/pybind11/options.h
pybind11/include/pybind11/pybind11.h
pybind11/include/pybind11/pytypes.h
pybind11/include/pybind11/stl.h
pybind11/include/pybind11/stl_bind.h
pybind11/include/pybind11/type_caster_pyobject_ptr.h
pybind11/include/pybind11/typing.h
pybind11/include/pybind11/detail/class.h
pybind11/include/pybind11/detail/common.h
pybind11/include/pybind11/detail/descr.h
pybind11/include/pybind11/detail/init.h
pybind11/include/pybind11/detail/internals.h
pybind11/include/pybind11/detail/type_caster_base.h
pybind11/include/pybind11/detail/typeid.h
pybind11/include/pybind11/eigen/common.h
pybind11/include/pybind11/eigen/matrix.h
pybind11/include/pybind11/eigen/tensor.h
pybind11/include/pybind11/stl/filesystem.h
pybind11/tools/FindCatch.cmake
pybind11/tools/FindEigen3.cmake
pybind11/tools/FindPythonLibsNew.cmake
pybind11/tools/JoinPaths.cmake
pybind11/tools/check-style.sh
pybind11/tools/cmake_uninstall.cmake.in
pybind11/tools/codespell_ignore_lines_from_errors.py
pybind11/tools/libsize.py
pybind11/tools/make_changelog.py
pybind11/tools/pybind11.pc.in
pybind11/tools/pybind11Common.cmake
pybind11/tools/pybind11Config.cmake.in
pybind11/tools/pybind11NewTools.cmake
pybind11/tools/pybind11Tools.cmake
pybind11/tools/pyproject.toml
pybind11/tools/setup_global.py.in
