Metadata-Version: 2.4
Name: llnl-ssapy
Version: 1.1.3
Summary: A fast, flexible, high-fidelity orbital modeling and analysis tool for orbits spanning from low-Earth orbit into the cislunar regime.
Author-email: LLNL SSAPy Software Team <yeagerastro@gmail.com>
License: MIT License
Project-URL: Homepage, https://github.com/LLNL/SSAPy
Project-URL: Issues, https://github.com/LLNL/SSAPy/issues
Project-URL: Documentation, https://software.llnl.gov/SSAPy/
Classifier: Programming Language :: Python :: 3
Classifier: Operating System :: OS Independent
Requires-Python: >=3.8
License-File: LICENSE
License-File: NOTICE
Requires-Dist: numpy<2.0
Requires-Dist: scipy
Requires-Dist: astropy
Requires-Dist: pyerfa
Requires-Dist: emcee
Requires-Dist: lmfit
Requires-Dist: sgp4
Requires-Dist: matplotlib
Requires-Dist: pandas
Requires-Dist: h5py
Requires-Dist: pypdf2
Requires-Dist: imageio
Requires-Dist: ipython
Requires-Dist: ipyvolume
Requires-Dist: ipython_genutils
Requires-Dist: jplephem
Requires-Dist: tqdm
Requires-Dist: myst-parser
Requires-Dist: graphviz
Dynamic: license-file
